hua_rs-0.1.0.dist-info/METADATA
hua_rs-0.1.0.dist-info/WHEEL
hua_rs-0.1.0.dist-info/license_files/LICENSE
hua_rs/__init__.py
hua_rs/hua_rs.pypy39-pp73-x86-linux-gnu.so
hua_rs-0.1.0.dist-info/RECORD
