Metadata-Version: 2.3
Name: hua_rs
Version: 0.1.0
Classifier: Programming Language :: Rust
Classifier: Programming Language :: Python :: Implementation :: CPython
Classifier: Programming Language :: Python :: Implementation :: PyPy
License-File: LICENSE
Summary: Heirarchical Uncertainty Aggregation (Park et al., 2022) in Rust.
Home-Page: https://github.com/Y-T-G/hua_rs
Author: Mohammed Yasin <>
License: MIT
Requires-Python: >=3.8
Project-URL: Source Code, https://github.com/Y-T-G/hua_rs
